{
  "id": "174404ca-c029-409a-8b62-e94802362ff4",
  "prevId": "c7d4881f-4f6b-4378-93f7-8fd6a63428dd",
  "version": "7",
  "dialect": "postgresql",
  "tables": {
    "public.account": {
      "name": "account",
      "schema": "",
      "columns": {
        "user_id": {
          "name": "user_id",
          "type": "text",
          "primaryKey": false,
          "notNull": true
        },
        "type": {
          "name": "type",
          "type": "text",
          "primaryKey": false,
          "notNull": true
        },
        "provider": {
          "name": "provider",
          "type": "text",
          "primaryKey": false,
          "notNull": true
        },
        "provider_account_id": {
          "name": "provider_account_id",
          "type": "text",
          "primaryKey": false,
          "notNull": true
        },
        "refresh_token": {
          "name": "refresh_token",
          "type": "text",
          "primaryKey": false,
          "notNull": false
        },
        "access_token": {
          "name": "access_token",
          "type": "text",
          "primaryKey": false,
          "notNull": false
        },
        "expires_at": {
          "name": "expires_at",
          "type": "integer",
          "primaryKey": false,
          "notNull": false
        },
        "token_type": {
          "name": "token_type",
          "type": "text",
          "primaryKey": false,
          "notNull": false
        },
        "scope": {
          "name": "scope",
          "type": "text",
          "primaryKey": false,
          "notNull": false
        },
        "id_token": {
          "name": "id_token",
          "type": "text",
          "primaryKey": false,
          "notNull": false
        },
        "session_state": {
          "name": "session_state",
          "type": "text",
          "primaryKey": false,
          "notNull": false
        }
      },
      "indexes": {},
      "foreignKeys": {},
      "compositePrimaryKeys": {
        "account_provider_provider_account_id_pk": {
          "name": "account_provider_provider_account_id_pk",
          "columns": [
            "provider",
            "provider_account_id"
          ]
        }
      },
      "uniqueConstraints": {},
      "checkConstraints": {}
    },
    "public.authenticators": {
      "name": "authenticators",
      "schema": "",
      "columns": {
        "credential_id": {
          "name": "credential_id",
          "type": "text",
          "primaryKey": false,
          "notNull": true
        },
        "user_id": {
          "name": "user_id",
          "type": "text",
          "primaryKey": false,
          "notNull": true
        },
        "provider_account_id": {
          "name": "provider_account_id",
          "type": "text",
          "primaryKey": false,
          "notNull": true
        },
        "credential_public_key": {
          "name": "credential_public_key",
          "type": "text",
          "primaryKey": false,
          "notNull": true
        },
        "counter": {
          "name": "counter",
          "type": "integer",
          "primaryKey": false,
          "notNull": true
        },
        "credential_device_type": {
          "name": "credential_device_type",
          "type": "text",
          "primaryKey": false,
          "notNull": true
        },
        "credential_backed_up": {
          "name": "credential_backed_up",
          "type": "boolean",
          "primaryKey": false,
          "notNull": true
        },
        "transports": {
          "name": "transports",
          "type": "text",
          "primaryKey": false,
          "notNull": false
        }
      },
      "indexes": {},
      "foreignKeys": {
        "authenticators_user_id_users_id_fk": {
          "name": "authenticators_user_id_users_id_fk",
          "tableFrom": "authenticators",
          "tableTo": "users",
          "columnsFrom": [
            "user_id"
          ],
          "columnsTo": [
            "id"
          ],
          "onDelete": "cascade",
          "onUpdate": "no action"
        }
      },
      "compositePrimaryKeys": {
        "authenticators_user_id_credential_id_pk": {
          "name": "authenticators_user_id_credential_id_pk",
          "columns": [
            "credential_id",
            "user_id"
          ]
        }
      },
      "uniqueConstraints": {
        "authenticators_credential_id_unique": {
          "name": "authenticators_credential_id_unique",
          "nullsNotDistinct": false,
          "columns": [
            "credential_id"
          ]
        }
      },
      "checkConstraints": {}
    },
    "public.Hashtags": {
      "name": "Hashtags",
      "schema": "",
      "columns": {
        "id": {
          "name": "id",
          "type": "serial",
          "primaryKey": true,
          "notNull": true
        },
        "tag": {
          "name": "tag",
          "type": "varchar(100)",
          "primaryKey": false,
          "notNull": true
        }
      },
      "indexes": {
        "Hashtags_tag_key": {
          "name": "Hashtags_tag_key",
          "columns": [
            {
              "expression": "tag",
              "isExpression": false,
              "asc": true,
              "nulls": "last"
            }
          ],
          "isUnique": true,
          "concurrently": false,
          "method": "btree",
          "with": {}
        }
      },
      "foreignKeys": {},
      "compositePrimaryKeys": {},
      "uniqueConstraints": {},
      "checkConstraints": {}
    },
    "public._HashtagsToTweet": {
      "name": "_HashtagsToTweet",
      "schema": "",
      "columns": {
        "A": {
          "name": "A",
          "type": "integer",
          "primaryKey": false,
          "notNull": true
        },
        "B": {
          "name": "B",
          "type": "text",
          "primaryKey": false,
          "notNull": true
        }
      },
      "indexes": {
        "_HashtagsToTweet_AB_unique": {
          "name": "_HashtagsToTweet_AB_unique",
          "columns": [
            {
              "expression": "A",
              "isExpression": false,
              "asc": true,
              "nulls": "last"
            },
            {
              "expression": "B",
              "isExpression": false,
              "asc": true,
              "nulls": "last"
            }
          ],
          "isUnique": true,
          "concurrently": false,
          "method": "btree",
          "with": {}
        },
        "_HashtagsToTweet_B_index": {
          "name": "_HashtagsToTweet_B_index",
          "columns": [
            {
              "expression": "B",
              "isExpression": false,
              "asc": true,
              "nulls": "last"
            }
          ],
          "isUnique": false,
          "concurrently": false,
          "method": "btree",
          "with": {}
        }
      },
      "foreignKeys": {
        "_HashtagsToTweet_A_fkey": {
          "name": "_HashtagsToTweet_A_fkey",
          "tableFrom": "_HashtagsToTweet",
          "tableTo": "Hashtags",
          "columnsFrom": [
            "A"
          ],
          "columnsTo": [
            "id"
          ],
          "onDelete": "cascade",
          "onUpdate": "cascade"
        },
        "_HashtagsToTweet_B_fkey": {
          "name": "_HashtagsToTweet_B_fkey",
          "tableFrom": "_HashtagsToTweet",
          "tableTo": "Tweet",
          "columnsFrom": [
            "B"
          ],
          "columnsTo": [
            "id"
          ],
          "onDelete": "cascade",
          "onUpdate": "cascade"
        }
      },
      "compositePrimaryKeys": {},
      "uniqueConstraints": {},
      "checkConstraints": {}
    },
    "public.Likes": {
      "name": "Likes",
      "schema": "",
      "columns": {
        "user_id": {
          "name": "user_id",
          "type": "text",
          "primaryKey": false,
          "notNull": true
        },
        "tweet_id": {
          "name": "tweet_id",
          "type": "text",
          "primaryKey": false,
          "notNull": true
        },
        "liked_at": {
          "name": "liked_at",
          "type": "timestamp(3)",
          "primaryKey": false,
          "notNull": true,
          "default": "CURRENT_TIMESTAMP"
        }
      },
      "indexes": {},
      "foreignKeys": {
        "Likes_user_id_fkey": {
          "name": "Likes_user_id_fkey",
          "tableFrom": "Likes",
          "tableTo": "users",
          "columnsFrom": [
            "user_id"
          ],
          "columnsTo": [
            "id"
          ],
          "onDelete": "restrict",
          "onUpdate": "cascade"
        },
        "Likes_tweet_id_fkey": {
          "name": "Likes_tweet_id_fkey",
          "tableFrom": "Likes",
          "tableTo": "Tweet",
          "columnsFrom": [
            "tweet_id"
          ],
          "columnsTo": [
            "id"
          ],
          "onDelete": "restrict",
          "onUpdate": "cascade"
        }
      },
      "compositePrimaryKeys": {
        "Likes_pkey": {
          "name": "Likes_pkey",
          "columns": [
            "user_id",
            "tweet_id"
          ]
        }
      },
      "uniqueConstraints": {},
      "checkConstraints": {}
    },
    "public.media": {
      "name": "media",
      "schema": "",
      "columns": {
        "id": {
          "name": "id",
          "type": "text",
          "primaryKey": true,
          "notNull": true
        },
        "url": {
          "name": "url",
          "type": "text",
          "primaryKey": false,
          "notNull": true
        },
        "userId": {
          "name": "userId",
          "type": "text",
          "primaryKey": false,
          "notNull": false
        },
        "tweetId": {
          "name": "tweetId",
          "type": "text",
          "primaryKey": false,
          "notNull": false
        },
        "type": {
          "name": "type",
          "type": "text",
          "primaryKey": false,
          "notNull": true
        },
        "profilePicture": {
          "name": "profilePicture",
          "type": "boolean",
          "primaryKey": false,
          "notNull": true,
          "default": false
        },
        "createdAt": {
          "name": "createdAt",
          "type": "timestamp(3)",
          "primaryKey": false,
          "notNull": true,
          "default": "CURRENT_TIMESTAMP"
        }
      },
      "indexes": {},
      "foreignKeys": {
        "media_userId_fkey": {
          "name": "media_userId_fkey",
          "tableFrom": "media",
          "tableTo": "users",
          "columnsFrom": [
            "userId"
          ],
          "columnsTo": [
            "id"
          ],
          "onDelete": "set null",
          "onUpdate": "cascade"
        },
        "media_tweetId_fkey": {
          "name": "media_tweetId_fkey",
          "tableFrom": "media",
          "tableTo": "Tweet",
          "columnsFrom": [
            "tweetId"
          ],
          "columnsTo": [
            "id"
          ],
          "onDelete": "set null",
          "onUpdate": "cascade"
        }
      },
      "compositePrimaryKeys": {},
      "uniqueConstraints": {},
      "checkConstraints": {}
    },
    "public.Messages": {
      "name": "Messages",
      "schema": "",
      "columns": {
        "id": {
          "name": "id",
          "type": "text",
          "primaryKey": true,
          "notNull": true
        },
        "senderId": {
          "name": "senderId",
          "type": "text",
          "primaryKey": false,
          "notNull": true
        },
        "receiverId": {
          "name": "receiverId",
          "type": "text",
          "primaryKey": false,
          "notNull": true
        },
        "content": {
          "name": "content",
          "type": "text",
          "primaryKey": false,
          "notNull": true
        },
        "createdAt": {
          "name": "createdAt",
          "type": "timestamp(3)",
          "primaryKey": false,
          "notNull": true,
          "default": "CURRENT_TIMESTAMP"
        }
      },
      "indexes": {},
      "foreignKeys": {
        "Messages_senderId_fkey": {
          "name": "Messages_senderId_fkey",
          "tableFrom": "Messages",
          "tableTo": "users",
          "columnsFrom": [
            "senderId"
          ],
          "columnsTo": [
            "id"
          ],
          "onDelete": "restrict",
          "onUpdate": "cascade"
        },
        "Messages_receiverId_fkey": {
          "name": "Messages_receiverId_fkey",
          "tableFrom": "Messages",
          "tableTo": "users",
          "columnsFrom": [
            "receiverId"
          ],
          "columnsTo": [
            "id"
          ],
          "onDelete": "restrict",
          "onUpdate": "cascade"
        }
      },
      "compositePrimaryKeys": {},
      "uniqueConstraints": {},
      "checkConstraints": {}
    },
    "public.retweets": {
      "name": "retweets",
      "schema": "",
      "columns": {
        "id": {
          "name": "id",
          "type": "text",
          "primaryKey": true,
          "notNull": true
        },
        "user_id": {
          "name": "user_id",
          "type": "text",
          "primaryKey": false,
          "notNull": true
        },
        "parent_tweet_id": {
          "name": "parent_tweet_id",
          "type": "text",
          "primaryKey": false,
          "notNull": true
        },
        "created_at": {
          "name": "created_at",
          "type": "timestamp(3)",
          "primaryKey": false,
          "notNull": true,
          "default": "CURRENT_TIMESTAMP"
        }
      },
      "indexes": {},
      "foreignKeys": {
        "retweets_user_id_fkey": {
          "name": "retweets_user_id_fkey",
          "tableFrom": "retweets",
          "tableTo": "users",
          "columnsFrom": [
            "user_id"
          ],
          "columnsTo": [
            "id"
          ],
          "onDelete": "restrict",
          "onUpdate": "cascade"
        },
        "retweets_parent_tweet_id_fkey": {
          "name": "retweets_parent_tweet_id_fkey",
          "tableFrom": "retweets",
          "tableTo": "Tweet",
          "columnsFrom": [
            "parent_tweet_id"
          ],
          "columnsTo": [
            "id"
          ],
          "onDelete": "cascade",
          "onUpdate": "cascade"
        }
      },
      "compositePrimaryKeys": {},
      "uniqueConstraints": {},
      "checkConstraints": {}
    },
    "public.sessions": {
      "name": "sessions",
      "schema": "",
      "columns": {
        "session_token": {
          "name": "session_token",
          "type": "text",
          "primaryKey": true,
          "notNull": true
        },
        "user_id": {
          "name": "user_id",
          "type": "text",
          "primaryKey": false,
          "notNull": true
        },
        "expires": {
          "name": "expires",
          "type": "timestamp",
          "primaryKey": false,
          "notNull": true
        }
      },
      "indexes": {},
      "foreignKeys": {},
      "compositePrimaryKeys": {},
      "uniqueConstraints": {},
      "checkConstraints": {}
    },
    "public.Tweet": {
      "name": "Tweet",
      "schema": "",
      "columns": {
        "id": {
          "name": "id",
          "type": "text",
          "primaryKey": true,
          "notNull": true
        },
        "user_id": {
          "name": "user_id",
          "type": "text",
          "primaryKey": false,
          "notNull": true
        },
        "content": {
          "name": "content",
          "type": "text",
          "primaryKey": false,
          "notNull": true
        },
        "parent_tweet_id": {
          "name": "parent_tweet_id",
          "type": "text",
          "primaryKey": false,
          "notNull": false
        },
        "createdAt": {
          "name": "createdAt",
          "type": "timestamp(3)",
          "primaryKey": false,
          "notNull": true,
          "default": "CURRENT_TIMESTAMP"
        },
        "TweetType": {
          "name": "TweetType",
          "type": "TweetType",
          "typeSchema": "public",
          "primaryKey": false,
          "notNull": true,
          "default": "'DEFAULT'"
        }
      },
      "indexes": {},
      "foreignKeys": {
        "Tweet_user_id_fkey": {
          "name": "Tweet_user_id_fkey",
          "tableFrom": "Tweet",
          "tableTo": "users",
          "columnsFrom": [
            "user_id"
          ],
          "columnsTo": [
            "id"
          ],
          "onDelete": "restrict",
          "onUpdate": "cascade"
        },
        "Tweet_parent_tweet_id_fkey": {
          "name": "Tweet_parent_tweet_id_fkey",
          "tableFrom": "Tweet",
          "tableTo": "Tweet",
          "columnsFrom": [
            "parent_tweet_id"
          ],
          "columnsTo": [
            "id"
          ],
          "onDelete": "set null",
          "onUpdate": "cascade"
        }
      },
      "compositePrimaryKeys": {},
      "uniqueConstraints": {},
      "checkConstraints": {}
    },
    "public._UserFollows": {
      "name": "_UserFollows",
      "schema": "",
      "columns": {
        "A": {
          "name": "A",
          "type": "text",
          "primaryKey": false,
          "notNull": true
        },
        "B": {
          "name": "B",
          "type": "text",
          "primaryKey": false,
          "notNull": true
        }
      },
      "indexes": {
        "_UserFollows_AB_unique": {
          "name": "_UserFollows_AB_unique",
          "columns": [
            {
              "expression": "A",
              "isExpression": false,
              "asc": true,
              "nulls": "last"
            },
            {
              "expression": "B",
              "isExpression": false,
              "asc": true,
              "nulls": "last"
            }
          ],
          "isUnique": true,
          "concurrently": false,
          "method": "btree",
          "with": {}
        },
        "_UserFollows_B_index": {
          "name": "_UserFollows_B_index",
          "columns": [
            {
              "expression": "B",
              "isExpression": false,
              "asc": true,
              "nulls": "last"
            }
          ],
          "isUnique": false,
          "concurrently": false,
          "method": "btree",
          "with": {}
        }
      },
      "foreignKeys": {
        "_UserFollows_A_fkey": {
          "name": "_UserFollows_A_fkey",
          "tableFrom": "_UserFollows",
          "tableTo": "users",
          "columnsFrom": [
            "A"
          ],
          "columnsTo": [
            "id"
          ],
          "onDelete": "cascade",
          "onUpdate": "cascade"
        },
        "_UserFollows_B_fkey": {
          "name": "_UserFollows_B_fkey",
          "tableFrom": "_UserFollows",
          "tableTo": "users",
          "columnsFrom": [
            "B"
          ],
          "columnsTo": [
            "id"
          ],
          "onDelete": "cascade",
          "onUpdate": "cascade"
        }
      },
      "compositePrimaryKeys": {},
      "uniqueConstraints": {},
      "checkConstraints": {}
    },
    "public.UserSettings": {
      "name": "UserSettings",
      "schema": "",
      "columns": {
        "id": {
          "name": "id",
          "type": "text",
          "primaryKey": true,
          "notNull": true
        },
        "userId": {
          "name": "userId",
          "type": "text",
          "primaryKey": false,
          "notNull": true
        }
      },
      "indexes": {
        "UserSettings_userId_key": {
          "name": "UserSettings_userId_key",
          "columns": [
            {
              "expression": "userId",
              "isExpression": false,
              "asc": true,
              "nulls": "last"
            }
          ],
          "isUnique": true,
          "concurrently": false,
          "method": "btree",
          "with": {}
        }
      },
      "foreignKeys": {
        "UserSettings_userId_fkey": {
          "name": "UserSettings_userId_fkey",
          "tableFrom": "UserSettings",
          "tableTo": "users",
          "columnsFrom": [
            "userId"
          ],
          "columnsTo": [
            "id"
          ],
          "onDelete": "restrict",
          "onUpdate": "cascade"
        }
      },
      "compositePrimaryKeys": {},
      "uniqueConstraints": {},
      "checkConstraints": {}
    },
    "public.users": {
      "name": "users",
      "schema": "",
      "columns": {
        "id": {
          "name": "id",
          "type": "text",
          "primaryKey": true,
          "notNull": true
        },
        "name": {
          "name": "name",
          "type": "text",
          "primaryKey": false,
          "notNull": false
        },
        "email": {
          "name": "email",
          "type": "text",
          "primaryKey": false,
          "notNull": false
        },
        "email_verified": {
          "name": "email_verified",
          "type": "timestamp",
          "primaryKey": false,
          "notNull": false
        },
        "image": {
          "name": "image",
          "type": "text",
          "primaryKey": false,
          "notNull": false
        },
        "username": {
          "name": "username",
          "type": "text",
          "primaryKey": false,
          "notNull": false
        },
        "password_hash": {
          "name": "password_hash",
          "type": "text",
          "primaryKey": false,
          "notNull": false
        },
        "displayName": {
          "name": "displayName",
          "type": "text",
          "primaryKey": false,
          "notNull": false
        },
        "bio": {
          "name": "bio",
          "type": "text",
          "primaryKey": false,
          "notNull": false
        },
        "cover_image_url": {
          "name": "cover_image_url",
          "type": "text",
          "primaryKey": false,
          "notNull": false
        },
        "created_at": {
          "name": "created_at",
          "type": "timestamp",
          "primaryKey": false,
          "notNull": true,
          "default": "CURRENT_TIMESTAMP"
        },
        "updated_at": {
          "name": "updated_at",
          "type": "timestamp",
          "primaryKey": false,
          "notNull": true,
          "default": "CURRENT_TIMESTAMP"
        }
      },
      "indexes": {},
      "foreignKeys": {},
      "compositePrimaryKeys": {},
      "uniqueConstraints": {},
      "checkConstraints": {}
    },
    "public.verification_tokens": {
      "name": "verification_tokens",
      "schema": "",
      "columns": {
        "identifier": {
          "name": "identifier",
          "type": "text",
          "primaryKey": false,
          "notNull": true
        },
        "token": {
          "name": "token",
          "type": "text",
          "primaryKey": false,
          "notNull": true
        },
        "expires": {
          "name": "expires",
          "type": "timestamp",
          "primaryKey": false,
          "notNull": true
        }
      },
      "indexes": {},
      "foreignKeys": {},
      "compositePrimaryKeys": {
        "verification_tokens_identifier_token_pk": {
          "name": "verification_tokens_identifier_token_pk",
          "columns": [
            "identifier",
            "token"
          ]
        }
      },
      "uniqueConstraints": {},
      "checkConstraints": {}
    }
  },
  "enums": {
    "public.TweetType": {
      "name": "TweetType",
      "schema": "public",
      "values": [
        "DEFAULT",
        "REPLY",
        "QUOTE"
      ]
    }
  },
  "schemas": {},
  "sequences": {},
  "views": {},
  "_meta": {
    "columns": {},
    "schemas": {},
    "tables": {}
  }
}